Metadata-Version: 2.1
Name: geoip2nation
Version: 0.2.7
Summary: Convert ip addresses to a country using ip2nation db in memory.
Home-page: http://pypi.python.org/pypi/geoip2nation/
Author: Avi Asher
Author-email: aviasher@outlook.com
License: MIT
Platform: UNKNOWN
